ps2joycln/__init__.py
ps2joycln/__main__.py
ps2joycln-0.0.3.dist-info/LICENSE
ps2joycln-0.0.3.dist-info/METADATA
ps2joycln-0.0.3.dist-info/WHEEL
ps2joycln-0.0.3.dist-info/top_level.txt
ps2joycln-0.0.3.dist-info/RECORD
