Metadata-Version: 2.1
Name: ps2joycln
Version: 0.0.3
Summary: A client to convert UDP packets from a PS2 console into keyboard events
Author-email: Adler Neves <adlerosn@gmail.com>
Project-URL: Homepage, https://github.com/adlerosn/ps2joycln
Project-URL: Bug Tracker, https://github.com/adlerosn/ps2joycln/issues
Classifier: Programming Language :: Python :: 3
Classifier: License :: OSI Approved :: MIT License
Classifier: Operating System :: OS Independent
Requires-Python: >=3.10
License-File: LICENSE
Requires-Dist: keyboard (>=0.13.5)
